py_translate-1.0.3.dist-info/DESCRIPTION.rst
py_translate-1.0.3.dist-info/entry_points.txt
py_translate-1.0.3.dist-info/METADATA
py_translate-1.0.3.dist-info/metadata.json
py_translate-1.0.3.dist-info/pbr.json
py_translate-1.0.3.dist-info/RECORD
py_translate-1.0.3.dist-info/top_level.txt
py_translate-1.0.3.dist-info/WHEEL
translate/__init__.py
translate/__main__.py
translate/__version__.py
translate/coroutines.py
translate/languages.py
translate/translator.py
translate/etc/supported_translations.json
translate/tests/__init__.py
translate/tests/test_languages.py
translate/tests/test_translator.py
